{
  "indexes": [
    {
      "collectionGroup": "checklists",
      "queryScope": "COLLECTION",
      "fields": [
        {
          "fieldPath": "userId",
          "order": "ASCENDING"
        },
        {
          "fieldPath": "createdAt",
          "order": "DESCENDING"
        },
        {
          "fieldPath": "__name__",
          "order": "DESCENDING"
        }
      ],
      "density": "SPARSE_ALL"
    },
    {
      "collectionGroup": "documents",
      "queryScope": "COLLECTION",
      "fields": [
        {
          "fieldPath": "userId",
          "order": "ASCENDING"
        },
        {
          "fieldPath": "uploadedAt",
          "order": "DESCENDING"
        },
        {
          "fieldPath": "__name__",
          "order": "DESCENDING"
        }
      ],
      "density": "SPARSE_ALL"
    },
    {
      "collectionGroup": "summaries",
      "queryScope": "COLLECTION",
      "fields": [
        {
          "fieldPath": "documentId",
          "order": "ASCENDING"
        },
        {
          "fieldPath": "userId",
          "order": "ASCENDING"
        },
        {
          "fieldPath": "createdAt",
          "order": "DESCENDING"
        },
        {
          "fieldPath": "__name__",
          "order": "DESCENDING"
        }
      ],
      "density": "SPARSE_ALL"
    },
    {
      "collectionGroup": "ocr_results",
      "queryScope": "COLLECTION",
      "fields": [
        {
          "fieldPath": "fileName",
          "order": "ASCENDING"
        },
        {
          "fieldPath": "userId",
          "order": "ASCENDING"
        },
        {
          "fieldPath": "createdAt",
          "order": "DESCENDING"
        },
        {
          "fieldPath": "__name__",
          "order": "DESCENDING"
        }
      ],
      "density": "SPARSE_ALL"
    }
  ],
  "fieldOverrides": []
}